QuykHtml/__init__.py
QuykHtml-0.1.4.dist-info/LICENSE
QuykHtml-0.1.4.dist-info/METADATA
QuykHtml-0.1.4.dist-info/WHEEL
QuykHtml-0.1.4.dist-info/top_level.txt
QuykHtml-0.1.4.dist-info/RECORD
