Metadata-Version: 2.1
Name: QuykHtml
Version: 0.1.4
Summary: A python library that allows you to quickly and easily generate HTML templates and even create full-on websites.
Home-page: https://github.com/mwd1993/QuykHtml
Author: Marc D
Author-email: marcwarrelldavis@yahoo.com
Classifier: Intended Audience :: Developers
Classifier: License :: OSI Approved :: MIT License
Classifier: Programming Language :: Python :: 3
Classifier: Programming Language :: Python :: 3.6
Classifier: Programming Language :: Python :: 3.7
Classifier: Programming Language :: Python :: 3.8
Classifier: Programming Language :: Python :: 3.9
Requires-Python: >=3.6
License-File: LICENSE
